langchain_mcp_adapters-0.1.13.dist-info/METADATA
langchain_mcp_adapters-0.1.13.dist-info/WHEEL
langchain_mcp_adapters-0.1.13.dist-info/entry_points.txt
langchain_mcp_adapters-0.1.13.dist-info/licenses/LICENSE
langchain_mcp_adapters/__init__.py
langchain_mcp_adapters/callbacks.py
langchain_mcp_adapters/client.py
langchain_mcp_adapters/interceptors.py
langchain_mcp_adapters/prompts.py
langchain_mcp_adapters/resources.py
langchain_mcp_adapters/sessions.py
langchain_mcp_adapters/tools.py
langchain_mcp_adapters-0.1.13.dist-info/RECORD
