Metadata-Version: 2.4
Name: langchain-mcp-adapters
Version: 0.1.13
Summary: Make Anthropic Model Context Protocol (MCP) tools compatible with LangChain and LangGraph agents.
Author-Email: Vadym Barda <19161700+vbarda@users.noreply.github.com>
License-Expression: MIT
Project-URL: repository, https://www.github.com/langchain-ai/langchain-mcp-adapters
Requires-Python: >=3.10
Requires-Dist: langchain-core<2.0.0,>=0.3.36
Requires-Dist: mcp>=1.9.2
Requires-Dist: typing-extensions>=4.14.0
